trame_sandtank/__init__.py
trame_sandtank/app/__init__.py
trame_sandtank/app/engine.py
trame_sandtank/app/jupyter.py
trame_sandtank/app/main.py
trame_sandtank/app/ui.py
trame_sandtank/app/assets/HMEI-logo-light-bg.png
trame_sandtank/app/assets/PU-standard.png
trame_sandtank/app/assets/__init__.py
trame_sandtank/app/assets/favicon.png
trame_sandtank/app/assets/logo-arizona.png
trame_sandtank/app/assets/logo-igwmc.png
trame_sandtank/app/assets/logo-kitware.svg
trame_sandtank/app/assets/logo-mines.jpg
trame_sandtank/app/assets/run.sh
trame_sandtank/app/assets/__pycache__/__init__.cpython-39.pyc
trame_sandtank/html/__init__.py
trame_sandtank/html/module/__init__.py
trame_sandtank/html/module/serve/demo.html
trame_sandtank/html/module/serve/vue-trame_sandtank.common.js
trame_sandtank/html/module/serve/vue-trame_sandtank.common.js.map
trame_sandtank/html/module/serve/vue-trame_sandtank.css
trame_sandtank/html/module/serve/vue-trame_sandtank.umd.js
trame_sandtank/html/module/serve/vue-trame_sandtank.umd.js.map
trame_sandtank/html/module/serve/vue-trame_sandtank.umd.min.js
trame_sandtank/html/module/serve/vue-trame_sandtank.umd.min.js.map
trame_sandtank/html/module/serve/img/clay.0e361f27.jpg
trame_sandtank/html/module/serve/img/gravel.f25f48b3.jpg
trame_sandtank/html/module/serve/img/loam.acc6b392.jpg
trame_sandtank/html/module/serve/img/sand.e10f025c.jpg
trame_sandtank-1.0.0.dist-info/LICENSE
trame_sandtank-1.0.0.dist-info/METADATA
trame_sandtank-1.0.0.dist-info/WHEEL
trame_sandtank-1.0.0.dist-info/entry_points.txt
trame_sandtank-1.0.0.dist-info/top_level.txt
trame_sandtank-1.0.0.dist-info/RECORD
