Metadata-Version: 2.1
Name: trame-sandtank
Version: 1.0.0
Summary: ParFlow sandtank using trame
Home-page: UNKNOWN
Author: Kitware Inc.
License: Apache Software License
Keywords: Python,Interactive,Web,Application,Framework
Platform: UNKNOWN
Classifier: Development Status :: 1 - Planning
Classifier: Environment :: Web Environment
Classifier: License :: OSI Approved :: Apache Software License
Classifier: Natural Language :: English
Classifier: Operating System :: OS Independent
Classifier: Programming Language :: Python :: 3 :: Only
Classifier: Programming Language :: JavaScript
Classifier: Topic :: Software Development :: Libraries :: Application Frameworks
Classifier: Topic :: Software Development :: Libraries :: Python Modules
License-File: LICENSE
Requires-Dist: trame (>=2.0.0rc1)
Requires-Dist: vtk
Requires-Dist: pftools
